{
  "ts": 1780111052.8018696,
  "data": {
    "cik": "0000719413",
    "name": "HECLA MINING CO/DE/",
    "sector": "Mining & Quarrying of  Nonmetallic Minerals (No Fuels)",
    "eps": [
      {
        "year": 2025.0,
        "value": 0.49,
        "end": "2025-12-31"
      },
      {
        "year": 2024.0,
        "value": 0.06,
        "end": "2024-12-31"
      },
      {
        "year": 2023.0,
        "value": -0.14,
        "end": "2023-12-31"
      },
      {
        "year": 2022.0,
        "value": 0.07,
        "end": "2022-12-31"
      },
      {
        "year": 2021.0,
        "value": -0.19,
        "end": "2019-12-31"
      },
      {
        "year": 2020.0,
        "value": -0.03,
        "end": "2020-12-31"
      },
      {
        "year": 2019.0,
        "value": -0.2,
        "end": "2019-12-31"
      },
      {
        "year": 2018.0,
        "value": -0.07,
        "end": "2017-12-31"
      },
      {
        "year": 2017.0,
        "value": -0.06,
        "end": "2017-12-31"
      },
      {
        "year": 2016.0,
        "value": 0.18,
        "end": "2016-12-31"
      },
      {
        "year": 2015.0,
        "value": -0.23,
        "end": "2015-12-31"
      }
    ],
    "bvps": [
      {
        "year": 2020,
        "value": 3.2234218552822482
      },
      {
        "year": 2019,
        "value": 3.2444977561998534
      },
      {
        "year": 2018,
        "value": 3.502719042260942
      },
      {
        "year": 2017,
        "value": 3.66072971368487
      },
      {
        "year": 2016,
        "value": 3.699186824758601
      },
      {
        "year": 2015,
        "value": 3.51561718983148
      }
    ],
    "cur_ast": [
      {
        "year": 2025.0,
        "value": 629344000,
        "end": "2025-12-31"
      },
      {
        "year": 2024.0,
        "value": 214152000,
        "end": "2024-12-31"
      },
      {
        "year": 2023.0,
        "value": 260262000,
        "end": "2023-12-31"
      },
      {
        "year": 2022.0,
        "value": 267727000,
        "end": "2022-12-31"
      },
      {
        "year": 2021.0,
        "value": 341627000,
        "end": "2021-12-31"
      },
      {
        "year": 2020.0,
        "value": 284681000,
        "end": "2020-12-31"
      },
      {
        "year": 2019.0,
        "value": 179124000,
        "end": "2019-12-31"
      },
      {
        "year": 2018.0,
        "value": 321236000,
        "end": "2017-12-31"
      },
      {
        "year": 2017.0,
        "value": 320325000,
        "end": "2017-12-31"
      },
      {
        "year": 2016.0,
        "value": 303384000,
        "end": "2016-12-31"
      },
      {
        "year": 2015.0,
        "value": 269533000,
        "end": "2015-12-31"
      }
    ],
    "cur_lib": [
      {
        "year": 2025.0,
        "value": 231564000,
        "end": "2025-12-31"
      },
      {
        "year": 2024.0,
        "value": 197838000,
        "end": "2024-12-31"
      },
      {
        "year": 2023.0,
        "value": 157460000,
        "end": "2023-12-31"
      },
      {
        "year": 2022.0,
        "value": 178466000,
        "end": "2022-12-31"
      },
      {
        "year": 2021.0,
        "value": 147210000,
        "end": "2020-12-31"
      },
      {
        "year": 2020.0,
        "value": 149785000,
        "end": "2020-12-31"
      },
      {
        "year": 2019.0,
        "value": 116974000,
        "end": "2019-12-31"
      },
      {
        "year": 2018.0,
        "value": 136194000,
        "end": "2018-12-31"
      },
      {
        "year": 2017.0,
        "value": 126225000,
        "end": "2016-12-31"
      },
      {
        "year": 2016.0,
        "value": 127480000,
        "end": "2016-12-31"
      },
      {
        "year": 2015.0,
        "value": 127084000,
        "end": "2015-12-31"
      }
    ],
    "lt_debt": [
      {
        "year": 2019,
        "value": 504729000,
        "end": "2019-12-31"
      },
      {
        "year": 2018,
        "value": 532799000,
        "end": "2018-12-31"
      },
      {
        "year": 2017,
        "value": 502229000,
        "end": "2017-12-31"
      },
      {
        "year": 2016,
        "value": 500979000,
        "end": "2016-12-31"
      },
      {
        "year": 2015,
        "value": 500199000,
        "end": "2015-12-31"
      },
      {
        "year": 2014,
        "value": 498479000,
        "end": "2014-12-31"
      },
      {
        "year": 2013,
        "value": 490726000,
        "end": "2013-12-31"
      }
    ],
    "tot_lib": [
      {
        "year": 2025.0,
        "value": 968999000,
        "end": "2025-12-31"
      },
      {
        "year": 2024.0,
        "value": 941546000,
        "end": "2024-12-31"
      },
      {
        "year": 2023.0,
        "value": 1043000000,
        "end": "2023-12-31"
      },
      {
        "year": 2022.0,
        "value": 948205000,
        "end": "2022-12-31"
      },
      {
        "year": 2021.0,
        "value": 968021000,
        "end": "2021-12-31"
      },
      {
        "year": 2020.0,
        "value": 965384000,
        "end": "2020-12-31"
      },
      {
        "year": 2019.0,
        "value": 944885000,
        "end": "2019-12-31"
      },
      {
        "year": 2018.0,
        "value": 883881000,
        "end": "2017-12-31"
      },
      {
        "year": 2017.0,
        "value": 881075000,
        "end": "2017-12-31"
      },
      {
        "year": 2016.0,
        "value": 891833000,
        "end": "2016-12-31"
      },
      {
        "year": 2015.0,
        "value": 882999000,
        "end": "2015-12-31"
      }
    ],
    "equity": [
      {
        "year": 2025,
        "value": 2591646000
      },
      {
        "year": 2024,
        "value": 2039514000
      },
      {
        "year": 2023,
        "value": 1968104000
      },
      {
        "year": 2022,
        "value": 1978967000
      },
      {
        "year": 2021,
        "value": 1760787000
      },
      {
        "year": 2020,
        "value": 1713785000
      },
      {
        "year": 2019,
        "value": 1696534000
      },
      {
        "year": 2018,
        "value": 1690426000
      },
      {
        "year": 2017,
        "value": 1461277000
      },
      {
        "year": 2016,
        "value": 1462240000
      },
      {
        "year": 2015,
        "value": 1329300000
      }
    ],
    "shares": [
      {
        "year": 2020,
        "value": 531666371
      },
      {
        "year": 2019,
        "value": 522895723
      },
      {
        "year": 2018,
        "value": 482603937
      },
      {
        "year": 2017,
        "value": 399176425
      },
      {
        "year": 2016,
        "value": 395286875
      },
      {
        "year": 2015,
        "value": 378112840
      },
      {
        "year": 2014,
        "value": 367376863
      },
      {
        "year": 2013,
        "value": 342663381
      },
      {
        "year": 2012,
        "value": 285209848
      },
      {
        "year": 2011,
        "value": 285289924
      },
      {
        "year": 2010,
        "value": 258485666
      }
    ],
    "net_inc": [
      {
        "year": 2025.0,
        "value": 321712000,
        "end": "2025-12-31"
      },
      {
        "year": 2024.0,
        "value": 35802000,
        "end": "2024-12-31"
      },
      {
        "year": 2023.0,
        "value": -84217000,
        "end": "2023-12-31"
      },
      {
        "year": 2022.0,
        "value": -37348000,
        "end": "2022-12-31"
      },
      {
        "year": 2021.0,
        "value": -94909000,
        "end": "2019-12-31"
      },
      {
        "year": 2020.0,
        "value": -16790000,
        "end": "2020-12-31"
      },
      {
        "year": 2019.0,
        "value": -99557000,
        "end": "2019-12-31"
      },
      {
        "year": 2018.0,
        "value": -28520000,
        "end": "2017-12-31"
      },
      {
        "year": 2017.0,
        "value": -23519000,
        "end": "2017-12-31"
      },
      {
        "year": 2016.0,
        "value": 69547000,
        "end": "2016-12-31"
      },
      {
        "year": 2015.0,
        "value": -86968000,
        "end": "2015-12-31"
      }
    ],
    "revenue": [
      {
        "year": 2016,
        "value": 645957000,
        "end": "2016-12-31"
      },
      {
        "year": 2015,
        "value": 443567000,
        "end": "2015-12-31"
      },
      {
        "year": 2014,
        "value": 500781000,
        "end": "2014-12-31"
      },
      {
        "year": 2013,
        "value": 382589000,
        "end": "2013-12-31"
      }
    ],
    "dividends": [
      {
        "year": 2020,
        "value": 8600000,
        "end": "2020-12-31"
      },
      {
        "year": 2019,
        "value": 4914000,
        "end": "2019-12-31"
      },
      {
        "year": 2018,
        "value": 4393000,
        "end": "2018-12-31"
      },
      {
        "year": 2017,
        "value": 3867000,
        "end": "2016-12-31"
      },
      {
        "year": 2016,
        "value": 3867000,
        "end": "2016-12-31"
      },
      {
        "year": 2015,
        "value": 3739000,
        "end": "2015-12-31"
      },
      {
        "year": 2014,
        "value": 3547000,
        "end": "2014-12-31"
      },
      {
        "year": 2012,
        "value": 17121000,
        "end": "2012-12-31"
      },
      {
        "year": 2011,
        "value": 5592000,
        "end": "2011-12-31"
      }
    ],
    "gross_profit": [
      {
        "year": 2025.0,
        "value": 622203000,
        "end": "2025-12-31"
      },
      {
        "year": 2024.0,
        "value": 198210000,
        "end": "2024-12-31"
      },
      {
        "year": 2023.0,
        "value": 112949000,
        "end": "2023-12-31"
      },
      {
        "year": 2022.0,
        "value": 116156000,
        "end": "2022-12-31"
      },
      {
        "year": 2021.0,
        "value": 33830000,
        "end": "2019-12-31"
      },
      {
        "year": 2020.0,
        "value": 145703000,
        "end": "2020-12-31"
      },
      {
        "year": 2019.0,
        "value": 23399000,
        "end": "2019-12-31"
      },
      {
        "year": 2018.0,
        "value": 152449000,
        "end": "2017-12-31"
      },
      {
        "year": 2017.0,
        "value": 156986000,
        "end": "2017-12-31"
      },
      {
        "year": 2016.0,
        "value": 191506000,
        "end": "2016-12-31"
      },
      {
        "year": 2015.0,
        "value": 38511000,
        "end": "2015-12-31"
      }
    ],
    "op_income": [
      {
        "year": 2025.0,
        "value": 514795000,
        "end": "2025-12-31"
      },
      {
        "year": 2024.0,
        "value": 106276000,
        "end": "2024-12-31"
      },
      {
        "year": 2023.0,
        "value": -44674000,
        "end": "2023-12-31"
      },
      {
        "year": 2022.0,
        "value": 12438000,
        "end": "2022-12-31"
      },
      {
        "year": 2021.0,
        "value": -46678000,
        "end": "2019-12-31"
      },
      {
        "year": 2020.0,
        "value": 51581000,
        "end": "2020-12-31"
      },
      {
        "year": 2019.0,
        "value": -57109000,
        "end": "2019-12-31"
      },
      {
        "year": 2018.0,
        "value": 60106000,
        "end": "2017-12-31"
      },
      {
        "year": 2017.0,
        "value": 64643000,
        "end": "2017-12-31"
      },
      {
        "year": 2016.0,
        "value": 116944000,
        "end": "2016-12-31"
      },
      {
        "year": 2015.0,
        "value": -35611000,
        "end": "2015-12-31"
      }
    ],
    "op_cf": [
      {
        "year": 2025.0,
        "value": 562638000,
        "end": "2025-12-31"
      },
      {
        "year": 2024.0,
        "value": 218277000,
        "end": "2024-12-31"
      },
      {
        "year": 2023.0,
        "value": 75499000,
        "end": "2023-12-31"
      },
      {
        "year": 2022.0,
        "value": 89890000,
        "end": "2022-12-31"
      },
      {
        "year": 2021.0,
        "value": 120866000,
        "end": "2019-12-31"
      },
      {
        "year": 2020.0,
        "value": 180793000,
        "end": "2020-12-31"
      },
      {
        "year": 2019.0,
        "value": 120866000,
        "end": "2019-12-31"
      },
      {
        "year": 2018.0,
        "value": 115878000,
        "end": "2017-12-31"
      },
      {
        "year": 2017.0,
        "value": 115878000,
        "end": "2017-12-31"
      },
      {
        "year": 2016.0,
        "value": 225328000,
        "end": "2016-12-31"
      },
      {
        "year": 2015.0,
        "value": 106445000,
        "end": "2015-12-31"
      }
    ],
    "capex": [
      {
        "year": 2025.0,
        "value": 252389000,
        "end": "2025-12-31"
      },
      {
        "year": 2024.0,
        "value": 214492000,
        "end": "2024-12-31"
      },
      {
        "year": 2023.0,
        "value": 223887000,
        "end": "2023-12-31"
      },
      {
        "year": 2022.0,
        "value": 149378000,
        "end": "2022-12-31"
      },
      {
        "year": 2021.0,
        "value": 121421000,
        "end": "2019-12-31"
      },
      {
        "year": 2020.0,
        "value": 91016000,
        "end": "2020-12-31"
      },
      {
        "year": 2019.0,
        "value": 121421000,
        "end": "2019-12-31"
      },
      {
        "year": 2018.0,
        "value": 98038000,
        "end": "2017-12-31"
      },
      {
        "year": 2017.0,
        "value": 98038000,
        "end": "2017-12-31"
      },
      {
        "year": 2016.0,
        "value": 164788000,
        "end": "2016-12-31"
      },
      {
        "year": 2015.0,
        "value": 137443000,
        "end": "2015-12-31"
      }
    ]
  }
}